odoo10_addon_barcodes_multiline-10.0.1.0.1-nspkg.pth
odoo/addons/barcodes_multiline/README.rst
odoo/addons/barcodes_multiline/__init__.py
odoo/addons/barcodes_multiline/__manifest__.py
odoo/addons/barcodes_multiline/demo/__init__.py
odoo/addons/barcodes_multiline/demo/demo_wizard.py
odoo/addons/barcodes_multiline/demo/demo_wizard.xml
odoo/addons/barcodes_multiline/i18n/barcodes_multiline.pot
odoo/addons/barcodes_multiline/readme/CONTRIBUTORS.rst
odoo/addons/barcodes_multiline/readme/DESCRIPTION.rst
odoo/addons/barcodes_multiline/static/description/icon.png
odoo/addons/barcodes_multiline/static/description/index.html
odoo/addons/barcodes_multiline/static/src/js/barcode_events.js
odoo/addons/barcodes_multiline/static/src/js/tour.js
odoo/addons/barcodes_multiline/tests/__init__.py
odoo/addons/barcodes_multiline/tests/test_barcodes_multiline_ui.py
odoo/addons/barcodes_multiline/views/assets.xml
odoo/addons/barcodes_multiline/views/tour_views.xml
odoo10_addon_barcodes_multiline-10.0.1.0.1.dist-info/METADATA
odoo10_addon_barcodes_multiline-10.0.1.0.1.dist-info/WHEEL
odoo10_addon_barcodes_multiline-10.0.1.0.1.dist-info/namespace_packages.txt
odoo10_addon_barcodes_multiline-10.0.1.0.1.dist-info/top_level.txt
odoo10_addon_barcodes_multiline-10.0.1.0.1.dist-info/RECORD
