Metadata-Version: 2.1
Name: odoo10-addon-barcodes-multiline
Version: 10.0.1.0.1
Summary: It allows barcodes to span multiple lines.
Home-page: https://odoo-community.org/
Author: Sunflower IT, Odoo Community Association (OCA)
Author-email: support@odoo-community.org
License: AGPL-3
Platform: UNKNOWN
Classifier: Programming Language :: Python
Classifier: Framework :: Odoo
Classifier: License :: OSI Approved :: GNU Affero General Public License v3
Requires-Python: ~=2.7
Requires-Dist: odoo (<10.1dev,>=10.0)
